setup.py
pystackoverflow.egg-info/PKG-INFO
pystackoverflow.egg-info/SOURCES.txt
pystackoverflow.egg-info/dependency_links.txt
pystackoverflow.egg-info/entry_points.txt
pystackoverflow.egg-info/not-zip-safe
pystackoverflow.egg-info/requires.txt
pystackoverflow.egg-info/top_level.txt
stackoverflow/__init__.py
stackoverflow/auth_google.py
stackoverflow/auth_stackoverflow.py
stackoverflow/base.py
stackoverflow/cli.py
stackoverflow/stackexchange.py
stackoverflow/utils.py