Metadata-Version: 1.1
Name: pystackoverflow
Version: 1.2
Summary: Tool to use Stack Overflow services from CLI
Home-page: http://m0g.net
Author: Bernard `Guyzmo` Pratz
Author-email: stackoverflow@m0g.net
License: GPLv3
Keywords: stackoverflow api openid
Platform: UNKNOWN
Classifier: Development Status :: 4 - Beta
Classifier: License :: OSI Approved :: GNU General Public License v3 (GPLv3)
Classifier: Operating System :: Unix
